{"f1": 0.75315060872862, "timestamp": 1732978913, "checkpoint_dir_name": null, "done": false, "training_iteration": 1, "trial_id": "eb066_00002", "date": "2024-11-30_23-01-53", "time_this_iter_s": 42.727266788482666, "time_total_s": 42.727266788482666, "pid": 54824, "hostname": "Collins-MacBook-Pro.local", "node_ip": "127.0.0.1", "config": {"n_estimators": 71, "max_depth": 7, "max_features": "log2", "min_samples_split": 3, "min_samples_leaf": 2, "bootstrap": false}, "time_since_restore": 42.727266788482666, "iterations_since_restore": 1}
