{"f1": 0.9600867067361911, "timestamp": 1729722261, "checkpoint_dir_name": null, "done": true, "training_iteration": 1, "trial_id": "eb4db_00021", "date": "2024-10-24_06-24-21", "time_this_iter_s": 9022.40062713623, "time_total_s": 9022.40062713623, "pid": 25514, "hostname": "Collins-MacBook-Pro.local", "node_ip": "127.0.0.1", "config": {"n_estimators": 296, "max_depth": 16, "max_features": null, "min_samples_split": 4, "min_samples_leaf": 1, "bootstrap": true}, "time_since_restore": 9022.40062713623, "iterations_since_restore": 1}
