{"f1": 0.9262244755801458, "timestamp": 1729718260, "checkpoint_dir_name": null, "done": true, "training_iteration": 1, "trial_id": "eb4db_00002", "date": "2024-10-24_05-17-40", "time_this_iter_s": 5710.14528799057, "time_total_s": 5710.14528799057, "pid": 25117, "hostname": "Collins-MacBook-Pro.local", "node_ip": "127.0.0.1", "config": {"n_estimators": 149, "max_depth": 10, "max_features": null, "min_samples_split": 7, "min_samples_leaf": 1, "bootstrap": false}, "time_since_restore": 5710.14528799057, "iterations_since_restore": 1}
