{"f1": 0.75315060872862, "timestamp": 1732980773, "checkpoint_dir_name": null, "done": false, "training_iteration": 1, "trial_id": "427e3_00002", "date": "2024-11-30_23-32-53", "time_this_iter_s": 39.522785902023315, "time_total_s": 39.522785902023315, "pid": 56610, "hostname": "Collins-MacBook-Pro.local", "node_ip": "127.0.0.1", "config": {"n_estimators": 71, "max_depth": 7, "max_features": "log2", "min_samples_split": 3, "min_samples_leaf": 2, "bootstrap": false}, "time_since_restore": 39.522785902023315, "iterations_since_restore": 1}
